jsonrpc/model/__init__.py
jsonrpc/model/common.py
jsonrpc/model/error.py
jsonrpc/model/exceptions.py
jsonrpc/model/request.py
jsonrpc/model/response.py
jsonrpc_asyncio_model-0.1.0.dist-info/METADATA
jsonrpc_asyncio_model-0.1.0.dist-info/WHEEL
jsonrpc_asyncio_model-0.1.0.dist-info/top_level.txt
jsonrpc_asyncio_model-0.1.0.dist-info/RECORD
